pytest_echo/__init__.py
pytest_echo/plugin.py
pytest_echo/py.typed
pytest_echo/version.py
pytest_echo-2.0.1.dist-info/METADATA
pytest_echo-2.0.1.dist-info/WHEEL
pytest_echo-2.0.1.dist-info/entry_points.txt
pytest_echo-2.0.1.dist-info/licenses/LICENSE
pytest_echo-2.0.1.dist-info/RECORD
