Metadata-Version: 2.4
Name: pytest-echo
Version: 2.0.1
Summary: pytest plugin that allows to dump environment variables, package version and generic attributes
Project-URL: Homepage, https://github.com/pytest-dev/pytest-echo
Project-URL: Source, https://github.com/pytest-dev/pytest-echo
Project-URL: Tracker, https://github.com/pytest-dev/pytest-echo/issues
Maintainer-email: Stefano Apostolico <s.apostolico@gmail.com>
License: The MIT License
License-File: LICENSE
Keywords: echo,pytest
Classifier: Development Status :: 5 - Production/Stable
Classifier: Intended Audience :: Developers
Classifier: License :: OSI Approved :: MIT License
Classifier: Operating System :: OS Independent
Classifier: Programming Language :: Python
Classifier: Programming Language :: Python :: 3 :: Only
Classifier: Programming Language :: Python :: 3.8
Classifier: Programming Language :: Python :: 3.9
Classifier: Programming Language :: Python :: 3.10
Classifier: Programming Language :: Python :: 3.11
Classifier: Programming Language :: Python :: 3.12
Classifier: Programming Language :: Python :: 3.13
Classifier: Programming Language :: Python :: Implementation :: CPython
Classifier: Topic :: Software Development :: Libraries :: Python Modules
Requires-Python: >=3.8
Requires-Dist: pytest>=8.3.3
Requires-Dist: tomli>=2.0.1; python_version < '3.11'
